AUTHORS
CHANGELOG.rst
LICENSE
MANIFEST.in
README.rst
setup.py
django_rds_db_multitenant.egg-info/PKG-INFO
django_rds_db_multitenant.egg-info/SOURCES.txt
django_rds_db_multitenant.egg-info/dependency_links.txt
django_rds_db_multitenant.egg-info/requires.txt
django_rds_db_multitenant.egg-info/top_level.txt
rds_db_multitenant/__init__.py
rds_db_multitenant/__version__.py
rds_db_multitenant/mapper.py
rds_db_multitenant/middleware.py
rds_db_multitenant/threadlocal.py
rds_db_multitenant/utils.py
rds_db_multitenant/cache/__init__.py
rds_db_multitenant/cache/helper.py
rds_db_multitenant/db/__init__.py
rds_db_multitenant/db/backends/__init__.py
rds_db_multitenant/db/backends/mysql/__init__.py
rds_db_multitenant/db/backends/mysql/base.py